{
    "Apple Inc.": "AAPL",
    "Microsoft Corporation": "MSFT",
    "Meta Platforms, Inc.": "META",
    "Alphabet Inc. (Class A)": "GOOGL",
    "Amazon.com, Inc.": "AMZN",
    "NVIDIA Corporation": "NVDA",
    "Tesla, Inc.": "TSLA",
    "Advanced Micro Devices, Inc.": "AMD",
    "Intel Corporation": "INTC",
    "Netflix, Inc.": "NFLX",
    "The Coca-Cola Company": "KO",
    "PepsiCo, Inc.": "PEP",
    "Johnson & Johnson": "JNJ",
    "Procter & Gamble Co.": "PG",
    "Walmart Inc.": "WMT",
    "Costco Wholesale Corporation": "COST",
    "McDonald's Corporation": "MCD",
    "Visa Inc.": "V",
    "Mastercard Incorporated": "MA",
    "JPMorgan Chase & Co.": "JPM",
    "Bank of America Corporation": "BAC",
    "Citigroup Inc.": "C",
    "Goldman Sachs Group, Inc.": "GS",
    "Morgan Stanley": "MS",
    "Wells Fargo & Company": "WFC",
    "American Express Company": "AXP",
    "Berkshire Hathaway Inc.": "BRK.B",
    "The Home Depot, Inc.": "HD",
    "Lowe's Companies, Inc.": "LOW",
    "Target Corporation": "TGT",
    "Pfizer Inc.": "PFE",
    "Moderna, Inc.": "MRNA",
    "AbbVie Inc.": "ABBV",
    "Eli Lilly and Company": "LLY",
    "Gilead Sciences, Inc.": "GILD",
    "Merck & Co., Inc.": "MRK",
    "Bristol-Myers Squibb Company": "BMY",
    "Johnson Controls International plc": "JCI",
    "Raytheon Technologies Corporation": "RTX",
    "Lockheed Martin Corporation": "LMT",
    "General Dynamics Corporation": "GD",
    "Boeing Company": "BA",
    "Ford Motor Company": "F",
    "General Motors Company": "GM",
    "Rivian Automotive, Inc.": "RIVN",
    "Lucid Group, Inc.": "LCID",
    "NIO Inc.": "NIO",
    "Marathon Digital Holdings, Inc.": "MARA",
    "Coinbase Global, Inc.": "COIN",
    "Palantir Technologies Inc.": "PLTR",
    "Snowflake Inc.": "SNOW",
    "Datadog, Inc.": "DDOG",
    "Unity Software Inc.": "U",
    "Roblox Corporation": "RBLX",
    "Zoom Video Communications, Inc.": "ZM",
    "Twilio Inc.": "TWLO",
    "Atlassian Corporation": "TEAM",
    "Okta, Inc.": "OKTA",
    "MongoDB, Inc.": "MDB",
    "Cloudflare, Inc.": "NET",
    "Zscaler, Inc.": "ZS",
    "The Trade Desk, Inc.": "TTD",
    "Roku, Inc.": "ROKU",
    "Shopify Inc.": "SHOP",
    "Block, Inc.": "SQ",
    "Robinhood Markets, Inc.": "HOOD",
    "MicroStrategy Incorporated": "MSTR",
    "Upstart Holdings, Inc.": "UPST",
    "C3.ai, Inc.": "AI",
    "Rocket Companies, Inc.": "RKT",
    "SoFi Technologies, Inc.": "SOFI",
    "Altria Group, Inc.": "MO",
    "Philip Morris International Inc.": "PM",
    "Exxon Mobil Corporation": "XOM",
    "Chevron Corporation": "CVX",
    "Occidental Petroleum Corporation": "OXY",
    "ConocoPhillips": "COP",
    "Devon Energy Corporation": "DVN",
    "Enphase Energy, Inc.": "ENPH",
    "First Solar, Inc.": "FSLR",
    "SolarEdge Technologies, Inc.": "SEDG",
    "NextEra Energy, Inc.": "NEE",
    "Duke Energy Corporation": "DUK",
    "Southern Company": "SO",
    "Dominion Energy, Inc.": "D",
    "American Electric Power Company, Inc.": "AEP",
    "Constellation Energy Corporation": "CEG",
    "Waste Management, Inc.": "WM",
    "Republic Services, Inc.": "RSG",
    "Southwest Airlines Co.": "LUV",
    "Delta Air Lines, Inc.": "DAL",
    "United Airlines Holdings, Inc.": "UAL",
    "American Airlines Group Inc.": "AAL",
    "Booking Holdings Inc.": "BKNG",
    "Expedia Group, Inc.": "EXPE",
    "Carnival Corporation & plc": "CCL",
    "Royal Caribbean Cruises Ltd.": "RCL",
    "Airbnb, Inc.": "ABNB",
    "Uber Technologies, Inc.": "UBER",
    "Lyft, Inc.": "LYFT"
}